niaaml_gui/__init__.py
niaaml_gui/main.py
niaaml_gui/process_window_data.py
niaaml_gui/progress_bar.py
niaaml_gui/resources/icons/classifier.png
niaaml_gui/resources/icons/decision_tree.png
niaaml_gui/resources/icons/edit.png
niaaml_gui/resources/icons/encode.png
niaaml_gui/resources/icons/feature_selection.png
niaaml_gui/resources/icons/feature_transformation.png
niaaml_gui/resources/icons/file.png
niaaml_gui/resources/icons/fitness.png
niaaml_gui/resources/icons/folder.png
niaaml_gui/resources/icons/imputation.png
niaaml_gui/resources/icons/numbers.png
niaaml_gui/resources/icons/optimization_algorithm.png
niaaml_gui/resources/icons/placeholder.png
niaaml_gui/resources/icons/population.png
niaaml_gui/styles.qss
niaaml_gui/utils/pipeline_runner.py
niaaml_gui/utils/run_pipeline_subprocess.py
niaaml_gui/widgets/__init__.py
niaaml_gui/widgets/base_main_widget.py
niaaml_gui/widgets/connection_line.py
niaaml_gui/widgets/help_authors_widget.py
niaaml_gui/widgets/help_documentation_widget.py
niaaml_gui/widgets/help_license_widget.py
niaaml_gui/widgets/list_widget_custom.py
niaaml_gui/widgets/multi_selection_dialog.py
niaaml_gui/widgets/optimization_widget.py
niaaml_gui/widgets/pipeline_canvas.py
niaaml_gui/widgets/pipeline_controls.py
niaaml_gui/widgets/results_widget.py
niaaml_gui/widgets/sidebar.py
niaaml_gui/widgets/use_pipeline_widget.py
niaaml_gui/windows/__init__.py
niaaml_gui/windows/csv_editor_window.py
niaaml_gui/windows/pipeline_canvas_window.py
niaaml_gui/windows/process_window.py
niaaml_gui/windows/threads/__init__.py
niaaml_gui/windows/threads/optimize_thread.py
niaaml_gui/windows/threads/pipeline_runner_thread.py
niaaml_gui/windows/threads/run_thread.py
niaaml_gui-0.4.3.dist-info/LICENSE
niaaml_gui-0.4.3.dist-info/METADATA
niaaml_gui-0.4.3.dist-info/WHEEL
niaaml_gui-0.4.3.dist-info/entry_points.txt
niaaml_gui-0.4.3.dist-info/RECORD
