Metadata-Version: 2.1
Name: NiaAML-GUI
Version: 0.4.3
Summary: GUI for NiaAML Python package
Home-page: https://github.com/firefly-cpp/NiaAML-GUI
License: MIT
Keywords: classification,NiaPy,NiaAML,scikit-learn,nature-inspired algorithms,feature selection,preprocessing
Author: Luka Pečnik
Author-email: lukapecnik96@gmail.com
Requires-Python: >=3.10,<3.14
Classifier: License :: OSI Approved :: MIT License
Classifier: Programming Language :: Python :: 3
Classifier: Programming Language :: Python :: 3.10
Classifier: Programming Language :: Python :: 3.11
Classifier: Programming Language :: Python :: 3.12
Classifier: Programming Language :: Python :: 3.13
Requires-Dist: QtAwesome (>=1.2.3,<2.0.0)
Requires-Dist: niaaml (>=2.1.2,<3.0.0)
Requires-Dist: niapy (>=2.5.2,<3.0.0)
Requires-Dist: pyqt-feedback-flow (>=0.3.5,<0.4.0)
Requires-Dist: pyqt6 (>=6.6.0,<7.0.0)
Requires-Dist: pytest-qt (>=4.5.0,<5.0.0)
Requires-Dist: scikit-learn (>=1.6.1,<2.0.0)
Project-URL: Repository, https://github.com/firefly-cpp/NiaAML-GUI
